jax_toolkit/__init__.py
jax_toolkit/_version.py
jax_toolkit/losses/__init__.py
jax_toolkit/losses/bounding_box.py
jax_toolkit/losses/classification.py
jax_toolkit/losses/probabilistic.py
jax_toolkit/losses/regression.py
jax_toolkit/losses/utils.py
jax_toolkit/losses/tests/__init__.py
jax_toolkit/losses/tests/test_bounding_box.py
jax_toolkit/losses/tests/test_classification.py
jax_toolkit/losses/tests/test_probabilistic.py
jax_toolkit/losses/tests/test_regression.py
jax_toolkit/losses/tests/test_utils.py
jax_toolkit/metrics/__init__.py
jax_toolkit/metrics/classification.py
jax_toolkit/metrics/regression.py
jax_toolkit/metrics/tests/__init__.py
jax_toolkit/metrics/tests/test_classification.py
jax_toolkit/metrics/tests/test_regression.py
jax_toolkit-0.2.0.dist-info/LICENSE
jax_toolkit-0.2.0.dist-info/METADATA
jax_toolkit-0.2.0.dist-info/WHEEL
jax_toolkit-0.2.0.dist-info/top_level.txt
jax_toolkit-0.2.0.dist-info/RECORD
