Metadata-Version: 2.1
Name: jax-toolkit
Version: 0.2.0
Summary: A collection of jax functions to help with common machine/deep learning related functionality.
Home-page: https://github.com/asmith26/jax_toolkit.git
Author: asmith26
License: Apache-2.0
Platform: UNKNOWN
Classifier: Development Status :: 2 - Pre-Alpha
Classifier: Intended Audience :: Science/Research
Classifier: Programming Language :: Python :: 3
Requires-Python: >=3.7
Requires-Dist: jax
Requires-Dist: jaxlib
Provides-Extra: losses_utils
Requires-Dist: dm-haiku ; extra == 'losses_utils'
